{
  "version": "5.2.1",
  "flags": {},
  "shapes": [
    {
      "label": "icon",
      "points": [
        [
          39.77900552486188,
          318.232044198895
        ],
        [
          96.13259668508287,
          375.69060773480663
        ]
      ],
      "group_id": null,
      "description": "",
      "shape_type": "rectangle",
      "flags": {}
    },
    {
      "label": "icon",
      "points": [
        [
          67.40331491712708,
          19.337016574585633
        ],
        [
          114.9171270718232,
          62.98342541436464
        ]
      ],
      "group_id": null,
      "description": "",
      "shape_type": "rectangle",
      "flags": {}
    },
    {
      "label": "icon",
      "points": [
        [
          72.58563535911598,
          109.04972375690609
        ],
        [
          120.99447513812156,
          159.11602209944752
        ]
      ],
      "group_id": null,
      "description": "",
      "shape_type": "rectangle",
      "flags": {}
    },
    {
      "label": "icon",
      "points": [
        [
          97.23756906077352,
          89.50276243093924
        ],
        [
          145.8563535911602,
          141.4364640883978
        ]
      ],
      "group_id": null,
      "description": "",
      "shape_type": "rectangle",
      "flags": {}
    },
    {
      "label": "icon",
      "points": [
        [
          142.0662983425414,
          79.6353591160221
        ],
        [
          193.37016574585635,
          131.49171270718227
        ]
      ],
      "group_id": null,
      "description": "",
      "shape_type": "rectangle",
      "flags": {}
    },
    {
      "label": "icon",
      "points": [
        [
          124.04419889502756,
          2.762430939226519
        ],
        [
          169.61325966850825,
          44.19889502762431
        ]
      ],
      "group_id": null,
      "description": "",
      "shape_type": "rectangle",
      "flags": {}
    },
    {
      "label": "+",
      "points": [
        [
          122.09944751381217,
          118.23204419889503
        ]
      ],
      "group_id": null,
      "description": "",
      "shape_type": "point",
      "flags": {}
    },
    {
      "label": "+",
      "points": [
        [
          370.7182320441989,
          109.94475138121547
        ]
      ],
      "group_id": null,
      "description": "",
      "shape_type": "point",
      "flags": {}
    },
    {
      "label": "+",
      "points": [
        [
          489.5027624309392,
          43.0939226519337
        ]
      ],
      "group_id": null,
      "description": "",
      "shape_type": "point",
      "flags": {}
    },
    {
      "label": "+",
      "points": [
        [
          743.646408839779,
          23.756906077348066
        ]
      ],
      "group_id": null,
      "description": "",
      "shape_type": "point",
      "flags": {}
    },
    {
      "label": "+",
      "points": [
        [
          900.5524861878454,
          135.91160220994476
        ]
      ],
      "group_id": null,
      "description": "",
      "shape_type": "point",
      "flags": {}
    },
    {
      "label": "2",
      "points": [
        [
          30.93922651933702,
          251.93370165745864
        ],
        [
          66.85082872928177,
          302.76243093922653
        ]
      ],
      "group_id": null,
      "description": "",
      "shape_type": "rectangle",
      "flags": {}
    },
    {
      "label": "5",
      "points": [
        [
          7.734806629834255,
          1.6574585635359116
        ],
        [
          27.624309392265197,
          23.204419889502763
        ]
      ],
      "group_id": null,
      "description": "",
      "shape_type": "rectangle",
      "flags": {}
    },
    {
      "label": "4",
      "points": [
        [
          4.972375690607734,
          29.834254143646408
        ],
        [
          28.1767955801105,
          56.9060773480663
        ]
      ],
      "group_id": null,
      "description": "",
      "shape_type": "rectangle",
      "flags": {}
    },
    {
      "label": "3",
      "points": [
        [
          3.8674033149171265,
          58.011049723756905
        ],
        [
          24.861878453038678,
          80.11049723756906
        ]
      ],
      "group_id": null,
      "description": "",
      "shape_type": "rectangle",
      "flags": {}
    },
    {
      "label": "2",
      "points": [
        [
          5.524861878453038,
          84.5303867403315
        ],
        [
          30.93922651933702,
          110.49723756906077
        ]
      ],
      "group_id": null,
      "description": "",
      "shape_type": "rectangle",
      "flags": {}
    },
    {
      "label": "1",
      "points": [
        [
          4.972375690607734,
          111.04972375690608
        ],
        [
          27.071823204419893,
          136.46408839779005
        ]
      ],
      "group_id": null,
      "description": "",
      "shape_type": "rectangle",
      "flags": {}
    }
  ],
  "imagePath": "183166.jpg",
  "imageData": null,
  "imageHeight": 400,
  "imageWidth": 1000
}