{
  "version": "5.2.1",
  "flags": {},
  "shapes": [
    {
      "label": "icon",
      "points": [
        [
          39.67391304347827,
          318.2065217391304
        ],
        [
          97.28260869565219,
          375.81521739130426
        ]
      ],
      "group_id": null,
      "description": "",
      "shape_type": "rectangle",
      "flags": {}
    },
    {
      "label": "icon",
      "points": [
        [
          127.71739130434781,
          3.8043478260869534
        ],
        [
          173.3695652173913,
          47.01086956521739
        ]
      ],
      "group_id": null,
      "description": "",
      "shape_type": "rectangle",
      "flags": {}
    },
    {
      "label": "icon",
      "points": [
        [
          83.15217391304347,
          81.25
        ],
        [
          130.97826086956522,
          129.07608695652175
        ]
      ],
      "group_id": null,
      "description": "",
      "shape_type": "rectangle",
      "flags": {}
    },
    {
      "label": "icon",
      "points": [
        [
          101.6304347826087,
          26.90217391304347
        ],
        [
          147.8260869565217,
          69.29347826086953
        ]
      ],
      "group_id": null,
      "description": "",
      "shape_type": "rectangle",
      "flags": {}
    },
    {
      "label": "icon",
      "points": [
        [
          98.91304347826117,
          55.43478260869567
        ],
        [
          147.82608695652175,
          102.44565217391303
        ]
      ],
      "group_id": null,
      "description": "",
      "shape_type": "rectangle",
      "flags": {}
    },
    {
      "label": "icon",
      "points": [
        [
          65.21739130434786,
          104.61956521739138
        ],
        [
          113.58695652173913,
          153.5326086956522
        ]
      ],
      "group_id": null,
      "description": "",
      "shape_type": "rectangle",
      "flags": {}
    },
    {
      "label": "2",
      "points": [
        [
          30.97826086956522,
          248.64130434782606
        ],
        [
          64.67391304347827,
          292.1195652173913
        ]
      ],
      "group_id": null,
      "description": "",
      "shape_type": "rectangle",
      "flags": {}
    },
    {
      "label": "5",
      "points": [
        [
          7.734806629834255,
          1.6574585635359116
        ],
        [
          27.624309392265197,
          23.204419889502763
        ]
      ],
      "group_id": null,
      "description": "",
      "shape_type": "rectangle",
      "flags": {}
    },
    {
      "label": "4",
      "points": [
        [
          4.972375690607734,
          29.834254143646408
        ],
        [
          28.1767955801105,
          56.9060773480663
        ]
      ],
      "group_id": null,
      "description": "",
      "shape_type": "rectangle",
      "flags": {}
    },
    {
      "label": "3",
      "points": [
        [
          3.8674033149171265,
          58.011049723756905
        ],
        [
          24.861878453038678,
          80.11049723756906
        ]
      ],
      "group_id": null,
      "description": "",
      "shape_type": "rectangle",
      "flags": {}
    },
    {
      "label": "2",
      "points": [
        [
          5.524861878453038,
          84.5303867403315
        ],
        [
          30.93922651933702,
          110.49723756906077
        ]
      ],
      "group_id": null,
      "description": "",
      "shape_type": "rectangle",
      "flags": {}
    },
    {
      "label": "1",
      "points": [
        [
          4.972375690607734,
          111.04972375690608
        ],
        [
          27.071823204419893,
          136.46408839779005
        ]
      ],
      "group_id": null,
      "description": "",
      "shape_type": "rectangle",
      "flags": {}
    },
    {
      "label": "+",
      "points": [
        [
          89.67391304347827,
          127.44565217391305
        ]
      ],
      "group_id": null,
      "description": "",
      "shape_type": "point",
      "flags": {}
    },
    {
      "label": "+",
      "points": [
        [
          307.6086956521739,
          106.24999999999999
        ]
      ],
      "group_id": null,
      "description": "",
      "shape_type": "point",
      "flags": {}
    },
    {
      "label": "+",
      "points": [
        [
          520.6521739130435,
          77.9891304347826
        ]
      ],
      "group_id": null,
      "description": "",
      "shape_type": "point",
      "flags": {}
    },
    {
      "label": "+",
      "points": [
        [
          722.2826086956521,
          47.01086956521739
        ]
      ],
      "group_id": null,
      "description": "",
      "shape_type": "point",
      "flags": {}
    },
    {
      "label": "+",
      "points": [
        [
          951.0869565217391,
          25.27173913043478
        ]
      ],
      "group_id": null,
      "description": "",
      "shape_type": "point",
      "flags": {}
    }
  ],
  "imagePath": "183995.jpg",
  "imageData": null,
  "imageHeight": 400,
  "imageWidth": 1000
}