{
  "version": "5.2.1",
  "flags": {},
  "shapes": [
    {
      "label": "icon",
      "points": [
        [
          39.67391304347827,
          318.2065217391304
        ],
        [
          97.28260869565219,
          375.81521739130426
        ]
      ],
      "group_id": null,
      "description": "",
      "shape_type": "rectangle",
      "flags": {}
    },
    {
      "label": "icon",
      "points": [
        [
          69.02173913043477,
          0.0
        ],
        [
          115.21739130434784,
          33.423913043478265
        ]
      ],
      "group_id": null,
      "description": "",
      "shape_type": "rectangle",
      "flags": {}
    },
    {
      "label": "icon",
      "points": [
        [
          129.891304347826,
          69.83695652173911
        ],
        [
          180.43478260869566,
          122.55434782608695
        ]
      ],
      "group_id": null,
      "description": "",
      "shape_type": "rectangle",
      "flags": {}
    },
    {
      "label": "icon",
      "points": [
        [
          96.7391304347827,
          24.184782608695635
        ],
        [
          142.3913043478261,
          68.20652173913042
        ]
      ],
      "group_id": null,
      "description": "",
      "shape_type": "rectangle",
      "flags": {}
    },
    {
      "label": "icon",
      "points": [
        [
          45.652173913043484,
          97.0108695652174
        ],
        [
          94.02173913043478,
          145.3804347826087
        ]
      ],
      "group_id": null,
      "description": "",
      "shape_type": "rectangle",
      "flags": {}
    },
    {
      "label": "icon",
      "points": [
        [
          54.89130434782611,
          73.09782608695652
        ],
        [
          102.71739130434783,
          119.29347826086955
        ]
      ],
      "group_id": null,
      "description": "",
      "shape_type": "rectangle",
      "flags": {}
    },
    {
      "label": "3",
      "points": [
        [
          33.1521739130435,
          222.01086956521746
        ],
        [
          61.95652173913043,
          264.4021739130435
        ]
      ],
      "group_id": null,
      "description": "",
      "shape_type": "rectangle",
      "flags": {}
    },
    {
      "label": "5",
      "points": [
        [
          7.734806629834255,
          1.6574585635359116
        ],
        [
          27.624309392265197,
          23.204419889502763
        ]
      ],
      "group_id": null,
      "description": "",
      "shape_type": "rectangle",
      "flags": {}
    },
    {
      "label": "4",
      "points": [
        [
          4.972375690607734,
          29.834254143646408
        ],
        [
          28.1767955801105,
          56.9060773480663
        ]
      ],
      "group_id": null,
      "description": "",
      "shape_type": "rectangle",
      "flags": {}
    },
    {
      "label": "3",
      "points": [
        [
          3.8674033149171265,
          58.011049723756905
        ],
        [
          24.861878453038678,
          80.11049723756906
        ]
      ],
      "group_id": null,
      "description": "",
      "shape_type": "rectangle",
      "flags": {}
    },
    {
      "label": "2",
      "points": [
        [
          5.524861878453038,
          84.5303867403315
        ],
        [
          30.93922651933702,
          110.49723756906077
        ]
      ],
      "group_id": null,
      "description": "",
      "shape_type": "rectangle",
      "flags": {}
    },
    {
      "label": "1",
      "points": [
        [
          4.972375690607734,
          111.04972375690608
        ],
        [
          27.071823204419893,
          136.46408839779005
        ]
      ],
      "group_id": null,
      "description": "",
      "shape_type": "rectangle",
      "flags": {}
    },
    {
      "label": "+",
      "points": [
        [
          155.97826086956522,
          97.01086956521738
        ]
      ],
      "group_id": null,
      "description": "",
      "shape_type": "point",
      "flags": {}
    },
    {
      "label": "+",
      "points": [
        [
          322.2826086956522,
          46.46739130434783
        ]
      ],
      "group_id": null,
      "description": "",
      "shape_type": "point",
      "flags": {}
    },
    {
      "label": "+",
      "points": [
        [
          492.39130434782606,
          12.228260869565217
        ]
      ],
      "group_id": null,
      "description": "",
      "shape_type": "point",
      "flags": {}
    },
    {
      "label": "+",
      "points": [
        [
          676.6304347826086,
          125.81521739130433
        ]
      ],
      "group_id": null,
      "description": "",
      "shape_type": "point",
      "flags": {}
    },
    {
      "label": "+",
      "points": [
        [
          880.4347826086956,
          95.38043478260869
        ]
      ],
      "group_id": null,
      "description": "",
      "shape_type": "point",
      "flags": {}
    }
  ],
  "imagePath": "184061.jpg",
  "imageData": null,
  "imageHeight": 400,
  "imageWidth": 1000
}