{
  "version": "5.2.1",
  "flags": {},
  "shapes": [
    {
      "label": "icon",
      "points": [
        [
          39.67391304347827,
          318.2065217391304
        ],
        [
          97.28260869565219,
          375.81521739130426
        ]
      ],
      "group_id": null,
      "description": "",
      "shape_type": "rectangle",
      "flags": {}
    },
    {
      "label": "icon",
      "points": [
        [
          87.5,
          22.282608695652193
        ],
        [
          135.8695652173913,
          67.6630434782609
        ]
      ],
      "group_id": null,
      "description": "",
      "shape_type": "rectangle",
      "flags": {}
    },
    {
      "label": "icon",
      "points": [
        [
          139.1304347826088,
          77.71739130434783
        ],
        [
          191.84782608695653,
          130.16304347826087
        ]
      ],
      "group_id": null,
      "description": "",
      "shape_type": "rectangle",
      "flags": {}
    },
    {
      "label": "icon",
      "points": [
        [
          95.10869565217394,
          0.0
        ],
        [
          140.76086956521738,
          37.77173913043478
        ]
      ],
      "group_id": null,
      "description": "",
      "shape_type": "rectangle",
      "flags": {}
    },
    {
      "label": "icon",
      "points": [
        [
          82.06521739130436,
          81.79347826086953
        ],
        [
          129.89130434782606,
          128.53260869565216
        ]
      ],
      "group_id": null,
      "description": "",
      "shape_type": "rectangle",
      "flags": {}
    },
    {
      "label": "icon",
      "points": [
        [
          67.93478260869557,
          106.25000000000001
        ],
        [
          116.30434782608695,
          153.5326086956522
        ]
      ],
      "group_id": null,
      "description": "",
      "shape_type": "rectangle",
      "flags": {}
    },
    {
      "label": "1",
      "points": [
        [
          35.86956521739131,
          210.59782608695636
        ],
        [
          59.78260869565217,
          257.3369565217391
        ]
      ],
      "group_id": null,
      "description": "",
      "shape_type": "rectangle",
      "flags": {}
    },
    {
      "label": "5",
      "points": [
        [
          7.734806629834255,
          1.6574585635359116
        ],
        [
          27.624309392265197,
          23.204419889502763
        ]
      ],
      "group_id": null,
      "description": "",
      "shape_type": "rectangle",
      "flags": {}
    },
    {
      "label": "4",
      "points": [
        [
          4.972375690607734,
          29.834254143646408
        ],
        [
          28.1767955801105,
          56.9060773480663
        ]
      ],
      "group_id": null,
      "description": "",
      "shape_type": "rectangle",
      "flags": {}
    },
    {
      "label": "3",
      "points": [
        [
          3.8674033149171265,
          58.011049723756905
        ],
        [
          24.861878453038678,
          80.11049723756906
        ]
      ],
      "group_id": null,
      "description": "",
      "shape_type": "rectangle",
      "flags": {}
    },
    {
      "label": "2",
      "points": [
        [
          5.524861878453038,
          84.5303867403315
        ],
        [
          30.93922651933702,
          110.49723756906077
        ]
      ],
      "group_id": null,
      "description": "",
      "shape_type": "rectangle",
      "flags": {}
    },
    {
      "label": "1",
      "points": [
        [
          4.972375690607734,
          111.04972375690608
        ],
        [
          27.071823204419893,
          136.46408839779005
        ]
      ],
      "group_id": null,
      "description": "",
      "shape_type": "rectangle",
      "flags": {}
    },
    {
      "label": "+",
      "points": [
        [
          115.76086956521739,
          14.402173913043478
        ]
      ],
      "group_id": null,
      "description": "",
      "shape_type": "point",
      "flags": {}
    },
    {
      "label": "+",
      "points": [
        [
          292.39130434782606,
          129.6195652173913
        ]
      ],
      "group_id": null,
      "description": "",
      "shape_type": "point",
      "flags": {}
    },
    {
      "label": "+",
      "points": [
        [
          505.4347826086956,
          104.6195652173913
        ]
      ],
      "group_id": null,
      "description": "",
      "shape_type": "point",
      "flags": {}
    },
    {
      "label": "+",
      "points": [
        [
          766.8478260869565,
          104.6195652173913
        ]
      ],
      "group_id": null,
      "description": "",
      "shape_type": "point",
      "flags": {}
    },
    {
      "label": "+",
      "points": [
        [
          907.0652173913043,
          47.55434782608695
        ]
      ],
      "group_id": null,
      "description": "",
      "shape_type": "point",
      "flags": {}
    }
  ],
  "imagePath": "184248.jpg",
  "imageData": null,
  "imageHeight": 400,
  "imageWidth": 1000
}