{
  "version": "5.2.1",
  "flags": {},
  "shapes": [
    {
      "label": "icon",
      "points": [
        [
          40.331491712707184,
          317.1270718232044
        ],
        [
          97.79005524861878,
          376.7955801104972
        ]
      ],
      "group_id": null,
      "description": "",
      "shape_type": "rectangle",
      "flags": {}
    },
    {
      "label": "icon",
      "points": [
        [
          146.195652173913,
          41.84782608695652
        ],
        [
          194.56521739130434,
          90.4891304347826
        ]
      ],
      "group_id": null,
      "description": "",
      "shape_type": "rectangle",
      "flags": {}
    },
    {
      "label": "icon",
      "points": [
        [
          59.23913043478261,
          0.0
        ],
        [
          104.8913043478261,
          35.05434782608695
        ]
      ],
      "group_id": null,
      "description": "",
      "shape_type": "rectangle",
      "flags": {}
    },
    {
      "label": "icon",
      "points": [
        [
          50.54347826086956,
          72.554347826087
        ],
        [
          99.45652173913044,
          119.29347826086955
        ]
      ],
      "group_id": null,
      "description": "",
      "shape_type": "rectangle",
      "flags": {}
    },
    {
      "label": "icon",
      "points": [
        [
          34.78260869565216,
          43.749999999999986
        ],
        [
          83.69565217391305,
          87.77173913043478
        ]
      ],
      "group_id": null,
      "description": "",
      "shape_type": "rectangle",
      "flags": {}
    },
    {
      "label": "icon",
      "points": [
        [
          93.47826086956525,
          133.15217391304353
        ],
        [
          145.1086956521739,
          188.31521739130434
        ]
      ],
      "group_id": null,
      "description": "",
      "shape_type": "rectangle",
      "flags": {}
    },
    {
      "label": "+",
      "points": [
        [
          170.1086956521739,
          68.20652173913042
        ]
      ],
      "group_id": null,
      "description": "",
      "shape_type": "point",
      "flags": {}
    },
    {
      "label": "+",
      "points": [
        [
          280.9782608695652,
          15.489130434782608
        ]
      ],
      "group_id": null,
      "description": "",
      "shape_type": "point",
      "flags": {}
    },
    {
      "label": "+",
      "points": [
        [
          518.4782608695652,
          157.8804347826087
        ]
      ],
      "group_id": null,
      "description": "",
      "shape_type": "point",
      "flags": {}
    },
    {
      "label": "+",
      "points": [
        [
          675.0,
          96.46739130434781
        ]
      ],
      "group_id": null,
      "description": "",
      "shape_type": "point",
      "flags": {}
    },
    {
      "label": "+",
      "points": [
        [
          854.3478260869565,
          67.1195652173913
        ]
      ],
      "group_id": null,
      "description": "",
      "shape_type": "point",
      "flags": {}
    },
    {
      "label": "5",
      "points": [
        [
          32.06521739130436,
          259.5108695652174
        ],
        [
          68.47826086956522,
          304.0760869565217
        ]
      ],
      "group_id": null,
      "description": "",
      "shape_type": "rectangle",
      "flags": {}
    },
    {
      "label": "5",
      "points": [
        [
          7.734806629834255,
          1.6574585635359116
        ],
        [
          27.624309392265197,
          23.204419889502763
        ]
      ],
      "group_id": null,
      "description": "",
      "shape_type": "rectangle",
      "flags": {}
    },
    {
      "label": "4",
      "points": [
        [
          4.972375690607734,
          29.834254143646408
        ],
        [
          28.1767955801105,
          56.9060773480663
        ]
      ],
      "group_id": null,
      "description": "",
      "shape_type": "rectangle",
      "flags": {}
    },
    {
      "label": "3",
      "points": [
        [
          3.8674033149171265,
          58.011049723756905
        ],
        [
          24.861878453038678,
          80.11049723756906
        ]
      ],
      "group_id": null,
      "description": "",
      "shape_type": "rectangle",
      "flags": {}
    },
    {
      "label": "2",
      "points": [
        [
          5.524861878453038,
          84.5303867403315
        ],
        [
          30.93922651933702,
          110.49723756906077
        ]
      ],
      "group_id": null,
      "description": "",
      "shape_type": "rectangle",
      "flags": {}
    },
    {
      "label": "1",
      "points": [
        [
          4.972375690607734,
          111.04972375690608
        ],
        [
          27.071823204419893,
          136.46408839779005
        ]
      ],
      "group_id": null,
      "description": "",
      "shape_type": "rectangle",
      "flags": {}
    }
  ],
  "imagePath": "185428.jpg",
  "imageData": null,
  "imageHeight": 400,
  "imageWidth": 1000
}