{
  "version": "5.2.1",
  "flags": {},
  "shapes": [
    {
      "label": "1",
      "points": [
        [
          25.739644970414204,
          136.09467455621302
        ],
        [
          5.621301775147929,
          110.05917159763314
        ]
      ],
      "group_id": null,
      "description": "",
      "shape_type": "rectangle",
      "flags": {}
    },
    {
      "label": "2",
      "points": [
        [
          6.21301775147929,
          85.20710059171597
        ],
        [
          29.28994082840237,
          110.05917159763314
        ]
      ],
      "group_id": null,
      "description": "",
      "shape_type": "rectangle",
      "flags": {}
    },
    {
      "label": "3",
      "points": [
        [
          4.437869822485207,
          57.39644970414201
        ],
        [
          24.55621301775148,
          79.88165680473372
        ]
      ],
      "group_id": null,
      "description": "",
      "shape_type": "rectangle",
      "flags": {}
    },
    {
      "label": "4",
      "points": [
        [
          5.621301775147929,
          30.769230769230766
        ],
        [
          28.106508875739646,
          55.02958579881656
        ]
      ],
      "group_id": null,
      "description": "",
      "shape_type": "rectangle",
      "flags": {}
    },
    {
      "label": "5",
      "points": [
        [
          6.804733727810651,
          0.0
        ],
        [
          26.331360946745566,
          22.485207100591715
        ]
      ],
      "group_id": null,
      "description": "",
      "shape_type": "rectangle",
      "flags": {}
    },
    {
      "label": "+",
      "points": [
        [
          107.26495726495727,
          106.83760683760684
        ]
      ],
      "group_id": null,
      "description": "",
      "shape_type": "point",
      "flags": {}
    },
    {
      "label": "+",
      "points": [
        [
          341.45299145299145,
          89.74358974358975
        ]
      ],
      "group_id": null,
      "description": "",
      "shape_type": "point",
      "flags": {}
    },
    {
      "label": "+",
      "points": [
        [
          568.8034188034188,
          67.52136752136752
        ]
      ],
      "group_id": null,
      "description": "",
      "shape_type": "point",
      "flags": {}
    },
    {
      "label": "+",
      "points": [
        [
          703.8461538461538,
          18.803418803418808
        ]
      ],
      "group_id": null,
      "description": "",
      "shape_type": "point",
      "flags": {}
    },
    {
      "label": "+",
      "points": [
        [
          879.9145299145299,
          125.64102564102566
        ]
      ],
      "group_id": null,
      "description": "",
      "shape_type": "point",
      "flags": {}
    },
    {
      "label": "icon",
      "points": [
        [
          126.13908872901679,
          36.21103117505995
        ],
        [
          78.65707434052759,
          0.0
        ]
      ],
      "group_id": null,
      "description": "",
      "shape_type": "rectangle",
      "flags": {}
    },
    {
      "label": "icon",
      "points": [
        [
          140.52757793764988,
          40.28776978417266
        ],
        [
          190.8872901678657,
          89.68824940047962
        ]
      ],
      "group_id": null,
      "description": "",
      "shape_type": "rectangle",
      "flags": {}
    },
    {
      "label": "icon",
      "points": [
        [
          114.62829736211032,
          61.8705035971223
        ],
        [
          166.9064748201439,
          114.14868105515588
        ]
      ],
      "group_id": null,
      "description": "",
      "shape_type": "rectangle",
      "flags": {}
    },
    {
      "label": "icon",
      "points": [
        [
          81.29496402877697,
          79.85611510791367
        ],
        [
          130.93525179856115,
          129.49640287769785
        ]
      ],
      "group_id": null,
      "description": "",
      "shape_type": "rectangle",
      "flags": {}
    },
    {
      "label": "icon",
      "points": [
        [
          53.47721822541966,
          99.04076738609113
        ],
        [
          104.31654676258994,
          150.1199040767386
        ]
      ],
      "group_id": null,
      "description": "",
      "shape_type": "rectangle",
      "flags": {}
    },
    {
      "label": "icon",
      "points": [
        [
          97.3621103117506,
          375.29976019184653
        ],
        [
          40.28776978417266,
          319.42446043165467
        ]
      ],
      "group_id": null,
      "description": "",
      "shape_type": "rectangle",
      "flags": {}
    },
    {
      "label": "1",
      "points": [
        [
          57.55395683453237,
          256.8345323741007
        ],
        [
          35.4916067146283,
          214.1486810551559
        ]
      ],
      "group_id": null,
      "description": "",
      "shape_type": "rectangle",
      "flags": {}
    }
  ],
  "imagePath": "186239.jpg",
  "imageData": null,
  "imageHeight": 400,
  "imageWidth": 1000
}