{
  "version": "5.2.1",
  "flags": {},
  "shapes": [
    {
      "label": "1",
      "points": [
        [
          25.739644970414204,
          136.09467455621302
        ],
        [
          5.621301775147929,
          110.05917159763314
        ]
      ],
      "group_id": null,
      "description": "",
      "shape_type": "rectangle",
      "flags": {}
    },
    {
      "label": "2",
      "points": [
        [
          6.21301775147929,
          85.20710059171597
        ],
        [
          29.28994082840237,
          110.05917159763314
        ]
      ],
      "group_id": null,
      "description": "",
      "shape_type": "rectangle",
      "flags": {}
    },
    {
      "label": "3",
      "points": [
        [
          4.437869822485207,
          57.39644970414201
        ],
        [
          24.55621301775148,
          79.88165680473372
        ]
      ],
      "group_id": null,
      "description": "",
      "shape_type": "rectangle",
      "flags": {}
    },
    {
      "label": "4",
      "points": [
        [
          5.621301775147929,
          30.769230769230766
        ],
        [
          28.106508875739646,
          55.02958579881656
        ]
      ],
      "group_id": null,
      "description": "",
      "shape_type": "rectangle",
      "flags": {}
    },
    {
      "label": "5",
      "points": [
        [
          6.804733727810651,
          0.0
        ],
        [
          26.331360946745566,
          22.485207100591715
        ]
      ],
      "group_id": null,
      "description": "",
      "shape_type": "rectangle",
      "flags": {}
    },
    {
      "label": "+",
      "points": [
        [
          83.33333333333334,
          98.2905982905983
        ]
      ],
      "group_id": null,
      "description": "",
      "shape_type": "point",
      "flags": {}
    },
    {
      "label": "+",
      "points": [
        [
          293.5897435897436,
          71.7948717948718
        ]
      ],
      "group_id": null,
      "description": "",
      "shape_type": "point",
      "flags": {}
    },
    {
      "label": "+",
      "points": [
        [
          560.2564102564103,
          62.39316239316241
        ]
      ],
      "group_id": null,
      "description": "",
      "shape_type": "point",
      "flags": {}
    },
    {
      "label": "+",
      "points": [
        [
          717.5213675213676,
          18.803418803418808
        ]
      ],
      "group_id": null,
      "description": "",
      "shape_type": "point",
      "flags": {}
    },
    {
      "label": "+",
      "points": [
        [
          866.2393162393163,
          120.51282051282053
        ]
      ],
      "group_id": null,
      "description": "",
      "shape_type": "point",
      "flags": {}
    },
    {
      "label": "icon",
      "points": [
        [
          141.27906976744185,
          38.372093023255815
        ],
        [
          93.31395348837209,
          0.0
        ]
      ],
      "group_id": null,
      "description": "",
      "shape_type": "rectangle",
      "flags": {}
    },
    {
      "label": "icon",
      "points": [
        [
          184.30232558139537,
          86.04651162790698
        ],
        [
          134.88372093023256,
          37.2093023255814
        ]
      ],
      "group_id": null,
      "description": "",
      "shape_type": "rectangle",
      "flags": {}
    },
    {
      "label": "icon",
      "points": [
        [
          67.44186046511628,
          45.348837209302324
        ],
        [
          118.6046511627907,
          91.86046511627907
        ]
      ],
      "group_id": null,
      "description": "",
      "shape_type": "rectangle",
      "flags": {}
    },
    {
      "label": "icon",
      "points": [
        [
          55.81395348837209,
          72.67441860465117
        ],
        [
          105.81395348837209,
          119.76744186046511
        ]
      ],
      "group_id": null,
      "description": "",
      "shape_type": "rectangle",
      "flags": {}
    },
    {
      "label": "icon",
      "points": [
        [
          38.08139534883721,
          95.63953488372093
        ],
        [
          88.95348837209302,
          145.34883720930233
        ]
      ],
      "group_id": null,
      "description": "",
      "shape_type": "rectangle",
      "flags": {}
    },
    {
      "label": "icon",
      "points": [
        [
          95.93023255813954,
          375.87209302325584
        ],
        [
          40.69767441860465,
          319.4767441860465
        ]
      ],
      "group_id": null,
      "description": "",
      "shape_type": "rectangle",
      "flags": {}
    },
    {
      "label": "3",
      "points": [
        [
          64.24418604651163,
          277.90697674418607
        ],
        [
          31.1046511627907,
          232.2674418604651
        ]
      ],
      "group_id": null,
      "description": "",
      "shape_type": "rectangle",
      "flags": {}
    }
  ],
  "imagePath": "186313.jpg",
  "imageData": null,
  "imageHeight": 400,
  "imageWidth": 1000
}